數位電路設計/Lab2/code/Lab2_BCD_9c_beh.v
module Lab2_BCD_9c_beh (input [3:0] BCD, output reg [3:0] BCD_9c);

    always @(*) begin
        BCD_9c[3] = ~BCD[3] & ~BCD[2] & ~BCD[1];
        BCD_9c[2] = BCD[2] ^ BCD[1];
        BCD_9c[1] = BCD[1];
        BCD_9c[0] = ~BCD[0]; 
    end   

endmodule

數位電路設計/Lab2/code/Lab2_BCD_9c_df.v
module Lab2_BCD_9c_df (input [3:0] BCD, output [3:0] BCD_9c);

    assign BCD_9c[3] = ~BCD[3] & ~BCD[2] & ~BCD[1];
    assign BCD_9c[2] = BCD[2] ^ BCD[1];
    assign BCD_9c[1] = BCD[1];
    assign BCD_9c[0] = ~BCD[0];    

endmodule

數位電路設計/Lab2/code/t_Lab2_BCD_9c.v
module	t_Lab2_BCD_9c();
	wire[3:0]	BCD_9c1, BCD_9c2;
	reg[3:0]	BCD;
	
	Lab2_BCD_9c_df	BCD_9c_df(BCD, BCD_9c1);
    Lab2_BCD_9c_beh BCD_9c_beh(BCD, BCD_9c2);
    integer i;
    
	initial	begin
		for(i=0;i<16;i++) begin
            BCD[0] = i[0];
            BCD[1] = i[1];
            BCD[2] = i[2];
            BCD[3] = i[3];
            #15;
        end

	end
	initial #200 $finish;

	//dump the result of simulation
	initial begin
		$dumpfile("Lab2_BCD_9c.vcd");
		$dumpvars;
	end
endmodule

數位電路設計/Lab2/code/Lab2_BCD_9c.vcd
$date
	Fri Apr 21 21:44:48 2023
$end
$version
	Icarus Verilog
$end
$timescale
	1s
$end
$scope module t_Lab2_BCD_9c $end
$var wire 4 ! BCD_9c2 [3:0] $end
$var wire 4 " BCD_9c1 [3:0] $end
$var reg 4 # BCD [3:0] $end
$var integer 32 $ i [31:0] $end
$scope module BCD_9c_beh $end
$var wire 4 % BCD [3:0] $end
$var reg 4 & BCD_9c [3:0] $end
$upscope $end
$scope module BCD_9c_df $end
$var wire 4 ' BCD [3:0] $end
$var wire 4 ( BCD_9c [3:0] $end
$upscope $end
$upscope $end
$enddefinitions $end
$comment Show the parameter values. $end
$dumpall
$end
#0
$dumpvars
b1001 (
b0 '
b1001 &
b0 %
b0 $
b0 #
b1001 "
b1001 !
$end
#15
b1000 "
b1000 (
b1000 !
b1000 &
b1 #
b1 %
b1 '
b1 $
#30
b111 "
b111 (
b111 !
b111 &
b10 #
b10 %
b10 '
b10 $
#45
b110 "
b110 (
b110 !
b110 &
b11 #
b11 %
b11 '
b11 $
#60
b101 "
b101 (
b101 !
b101 &
b100 #
b100 %
b100 '
b100 $
#75
b100 "
b100 (
b100 !
b100 &
b101 #
b101 %
b101 '
b101 $
#90
b11 "
b11 (
b11 !
b11 &
b110 #
b110 %
b110 '
b110 $
#105
b10 "
b10 (
b10 !
b10 &
b111 #
b111 %
b111 '
b111 $
#120
b1 "
b1 (
b1 !
b1 &
b1000 #
b1000 %
b1000 '
b1000 $
#135
b0 "
b0 (
b0 !
b0 &
b1001 #
b1001 %
b1001 '
b1001 $
#150
b111 "
b111 (
b111 !
b111 &
b1010 #
b1010 %
b1010 '
b1010 $
#165
b110 "
b110 (
b110 !
b110 &
b1011 #
b1011 %
b1011 '
b1011 $
#180
b101 "
b101 (
b101 !
b101 &
b1100 #
b1100 %
b1100 '
b1100 $
#195
b100 "
b100 (
b100 !
b100 &
b1101 #
b1101 %
b1101 '
b1101 $
