數位電路設計/Lab2/code/Lab2_half_add.v
module	Lab2_half_add (input a, b, output sum, cout);
	
    xor #(4) xor1(sum, a, b);
    and #(2) and1(cout, a, b);
endmodule

數位電路設計/Lab2/code/t_Lab2_half_add.v
module	t_Lab2_half_add();
	wire	sum, cout;
	reg		a, b;
	
	//instantiate device under test
	Lab2_half_add	M1(a, b, sum, cout);
	//apply inputs one at a time
	initial	begin
		a = 1'b0; b = 1'b0;
		#50;
        a = 1'b0; b = 1'b1;
        #50;
        a = 1'b1; b = 1'b0;
        #50;
        a = 1'b1; b = 1'b1;
	end
	initial #200 $finish;

	//dump the result of simulation
	initial begin
		$dumpfile("Lab2_half_add.vcd");
		$dumpvars;
	end
endmodule

數位電路設計/Lab2/code/Lab2_half_add.vcd
$date
	Thu Apr 20 22:26:49 2023
$end
$version
	Icarus Verilog
$end
$timescale
	1s
$end
$scope module t_Lab2_half_add $end
$var wire 1 ! sum $end
$var wire 1 " cout $end
$var reg 1 # a $end
$var reg 1 $ b $end
$scope module M1 $end
$var wire 1 # a $end
$var wire 1 $ b $end
$var wire 1 " cout $end
$var wire 1 ! sum $end
$upscope $end
$upscope $end
$enddefinitions $end
$comment Show the parameter values. $end
$dumpall
$end
#0
$dumpvars
0$
0#
x"
x!
$end
#2
0"
#4
0!
#50
1$
#54
1!
#100
0$
1#
#150
1$
#152
1"
#154
0!
