數位電路設計/Lab3/code/Lab3_D_Latch_gatelevel.v
module Lab3_D_Latch_gatelevel (input D, E, output Q, Qb);
    wire D, E;
    wire Q, Qb;
    wire D_inv, and_result1, and_result2;
    not #(1) not1(D_inv, D);
    and #(1) and1(and_result1, D_inv, E);
    and #(1) and2(and_result2, E, D);
    nor #(1) nor1(Q, and_result1, Qb);
    nor #(1) nor2(Qb, and_result2, Q);
endmodule

數位電路設計/Lab3/code/Lab3_D_FF_gatelevel.v
module Lab3_D_FF_gatelevel(input D, Clk, output Q, Qb);
    wire one2to, notclk, doublenot, nouse;
    not #(1) not1(notclk, Clk);
    not #(1) not2(doublenot, notclk);
    Lab3_D_Latch_gatelevel FF1(D, notclk, one2to, nouse);
    Lab3_D_Latch_gatelevel FF2(one2to, doublenot, Q, Qb);
endmodule

數位電路設計/Lab3/code/t_Lab3_D_FF_gatelevel.v
module t_Lab3_D_Latch_gatelevel();

    reg D, Clk;
    wire Q, Qb ;
    Lab3_D_FF_gatelevel FF(D, Clk, Q, Qb);
    initial begin
        Clk = 0;
        forever #5 Clk = ~Clk;
    end
    initial fork
        #0 D = 0;
        #7 D = 1;
        #17 D = 0;
        #37 D = 1;
        #47 D = 0;
        #57 D = 1;
        #77 D = 0;
        #81 D = 1;
        #100 $finish;
    join
    initial begin
		$dumpfile("t_Lab3_D_FF_gatelevel.vcd");
		$dumpvars;
	end



endmodule

數位電路設計/Lab3/code/t_Lab3_D_FF_gatelevel.vcd
$date
	Sat May 27 01:17:14 2023
$end
$version
	Icarus Verilog
$end
$timescale
	1s
$end
$scope module t_Lab3_D_Latch_gatelevel $end
$var wire 1 ! Qb $end
$var wire 1 " Q $end
$var reg 1 # Clk $end
$var reg 1 $ D $end
$scope module FF $end
$var wire 1 # Clk $end
$var wire 1 $ D $end
$var wire 1 % doublenot $end
$var wire 1 & notclk $end
$var wire 1 ' one2to $end
$var wire 1 ( nouse $end
$var wire 1 ! Qb $end
$var wire 1 " Q $end
$scope module FF1 $end
$var wire 1 $ D $end
$var wire 1 ) D_inv $end
$var wire 1 & E $end
$var wire 1 ' Q $end
$var wire 1 ( Qb $end
$var wire 1 * and_result1 $end
$var wire 1 + and_result2 $end
$upscope $end
$scope module FF2 $end
$var wire 1 ' D $end
$var wire 1 , D_inv $end
$var wire 1 % E $end
$var wire 1 " Q $end
$var wire 1 ! Qb $end
$var wire 1 - and_result1 $end
$var wire 1 . and_result2 $end
$upscope $end
$upscope $end
$upscope $end
$enddefinitions $end
$comment Show the parameter values. $end
$dumpall
$end
#0
$dumpvars
x.
x-
x,
x+
x*
x)
x(
x'
x&
x%
0$
0#
x"
x!
$end
#1
1)
0+
1&
#2
0%
1*
#3
0-
0.
0'
#4
1(
1,
#5
1#
#6
0&
#7
1%
0*
1$
#8
1-
0)
#9
0"
#10
1!
0#
#11
1&
#12
0%
1+
#13
0-
0(
#14
1'
#15
0,
1#
#16
0&
#17
1%
0+
0$
#18
1.
1)
#19
0!
#20
1"
0#
#21
1&
#22
0%
1*
#23
0.
0'
#24
1(
1,
#25
1#
#26
0&
#27
1%
0*
#28
1-
#29
0"
#30
1!
0#
#31
1&
#32
0%
1*
#33
0-
#35
1#
#36
0&
#37
1%
0*
1$
#38
1-
0)
#40
0#
#41
1&
#42
0%
1+
#43
0-
0(
#44
1'
#45
0,
1#
#46
0&
#47
1%
0+
0$
#48
1.
1)
#49
0!
#50
1"
0#
#51
1&
#52
0%
1*
#53
0.
0'
#54
1(
1,
#55
1#
#56
0&
#57
1%
0*
1$
#58
1-
0)
#59
0"
#60
1!
0#
#61
1&
#62
0%
1+
#63
0-
0(
#64
1'
#65
0,
1#
#66
0&
#67
1%
0+
#68
1.
#69
0!
#70
1"
0#
#71
1&
#72
0%
1+
#73
0.
#75
1#
#76
0&
#77
1%
0+
0$
#78
1.
1)
#80
0#
#81
1&
1$
#82
0%
1*
0)
1+
#83
0.
0'
0*
#84
1,
1'
#85
0,
1#
#86
0&
#87
1%
0+
#88
1.
#90
0#
#91
1&
#92
0%
1+
#93
0.
#95
1#
#96
0&
#97
1%
0+
#98
1.
