數位電路設計/Lab3/code/D_FF_AR.v
module D_FF_AR(input D, Clk, Rst, output Q);
    reg Q;
    always @ (posedge Clk, negedge Rst)
        if(!Rst) Q <= 1'b0;
        else Q <= D;
endmodule

數位電路設計/Lab3/code/Lab3_Converter_structure.v
module Lab3_Converter_structure(input X, Clk, Rst, output Z);

    wire ffinput1, ffinput2, ffinput3;
    wire ffoutput1, ffoutput2, ffoutput3;

    assign ffinput1 = (~X & ~ffoutput2) | (ffoutput1 & ~ffoutput2 & ~ffoutput3);
    assign ffinput2 = (ffoutput1 & ffoutput3) | (X & ~ffoutput2 & ffoutput3) | ( ~ffoutput1 & ffoutput2 & ~ffoutput3);
    assign ffinput3 = (~ffoutput3 & (ffoutput1 ^ ffoutput2)) | (X & ~ffoutput2 & (ffoutput1 | ~ffoutput3)) | (~X & ~ffoutput1 & ~ffoutput2 & ffoutput3);
    assign Z = (~X & ~ffoutput2 & (~ffoutput1 | ffoutput3)) | (X & ~ffoutput1 & ffoutput2) | (X & ffoutput1 & ~ffoutput2 & ~ffoutput3);

    D_FF_AR first(ffinput1, Clk, Rst, ffoutput1);
    D_FF_AR second(ffinput2, Clk, Rst, ffoutput2);
    D_FF_AR three(ffinput3, Clk, Rst, ffoutput3);
endmodule

數位電路設計/Lab3/code/Lab3_Converter_state_diagram.v
module Lab3_Converter_state_diagram (input X, Clk, Rst, output Z);

    reg [2:0] state, nextstate;
    reg Z;
    parameter S0 = 3'b000, S1 = 3'b001, S2 = 3'b010, S3 = 3'b011, S4 = 3'b100, S5 = 3'b101, S6 = 3'b110;

    always @(posedge Clk, negedge Rst)  // handle the update
        if(Rst == 0) state <= S0;
        else state <= nextstate;

    always @(state, X)              // handle the change of states
        case(state)
            S0: if(~X) nextstate = S4; else nextstate = S1;
            S1: if(~X) nextstate = S5; else nextstate = S2;
            S2: nextstate = S3;
            S3: nextstate = S0;
            S4: nextstate = S5;
            S5: if(~X) nextstate = S6; 
                else nextstate = S3;
            S6: nextstate = S0;
        endcase

    always @ (state, X)             // handle the output
        case (state)
            S0, S1, S5, S6: Z = ~X;
            S2, S3, S4: Z = X; 
        endcase

endmodule

數位電路設計/Lab3/code/t_Lab3_Converter.v
module t_Lab3_Converter();
    reg X, Clk, Rst;
    wire Z1, Z2;
    Lab3_Converter_state_diagram state_diagram(X, Clk, Rst, Z1);
    Lab3_Converter_structure structure(X, Clk, Rst, Z2);

    initial begin
        Clk = 0;
        #(9)
        forever begin 
            Clk = ~Clk; 
            #(5);
        end
    end

    integer i, j;

    initial begin
        Rst = 1;
        #(1);
        Rst = 0;
        #(1);
        Rst = 1;
    end
    initial begin
        for(i=3;i<13;i++)  begin
            for(j = 0;j<4;j++) begin
                X = i[j];
                #(10);
            end

        end
        $finish;
    end
    initial begin
		$dumpfile("t_Lab3_Converter.vcd");
		$dumpvars;
	end


endmodule

數位電路設計/Lab3/code/t_Lab3_Converter.vcd
$date
	Sat May 27 01:16:57 2023
$end
$version
	Icarus Verilog
$end
$timescale
	1s
$end
$scope module t_Lab3_Converter $end
$var wire 1 ! Z2 $end
$var wire 1 " Z1 $end
$var reg 1 # Clk $end
$var reg 1 $ Rst $end
$var reg 1 % X $end
$var integer 32 & i [31:0] $end
$var integer 32 ' j [31:0] $end
$scope module state_diagram $end
$var wire 1 # Clk $end
$var wire 1 $ Rst $end
$var wire 1 % X $end
$var parameter 3 ( S0 $end
$var parameter 3 ) S1 $end
$var parameter 3 * S2 $end
$var parameter 3 + S3 $end
$var parameter 3 , S4 $end
$var parameter 3 - S5 $end
$var parameter 3 . S6 $end
$var reg 1 " Z $end
$var reg 3 / nextstate [2:0] $end
$var reg 3 0 state [2:0] $end
$upscope $end
$scope module structure $end
$var wire 1 # Clk $end
$var wire 1 $ Rst $end
$var wire 1 % X $end
$var wire 1 ! Z $end
$var wire 1 1 ffinput1 $end
$var wire 1 2 ffinput2 $end
$var wire 1 3 ffinput3 $end
$var wire 1 4 ffoutput3 $end
$var wire 1 5 ffoutput2 $end
$var wire 1 6 ffoutput1 $end
$scope module first $end
$var wire 1 # Clk $end
$var wire 1 1 D $end
$var wire 1 $ Rst $end
$var reg 1 6 Q $end
$upscope $end
$scope module second $end
$var wire 1 # Clk $end
$var wire 1 2 D $end
$var wire 1 $ Rst $end
$var reg 1 5 Q $end
$upscope $end
$scope module three $end
$var wire 1 # Clk $end
$var wire 1 3 D $end
$var wire 1 $ Rst $end
$var reg 1 4 Q $end
$upscope $end
$upscope $end
$upscope $end
$enddefinitions $end
$comment Show the parameter values. $end
$dumpall
b110 .
b101 -
b100 ,
b11 +
b10 *
b1 )
b0 (
$end
#0
$dumpvars
x6
x5
x4
x3
x2
x1
bx 0
bx /
b0 '
b11 &
1%
1$
0#
x"
x!
$end
#1
0!
13
02
01
b1 /
0"
b0 0
06
05
04
0$
#2
1$
#9
03
12
b10 /
14
b1 0
1#
#10
b1 '
#14
0#
#19
13
1!
b11 /
1"
b10 0
15
04
1#
#20
0!
0"
0%
b10 '
#24
0#
#29
03
02
b0 /
14
b11 0
1#
#30
b11 '
#34
0#
#39
1!
11
1"
b100 /
b0 0
05
04
1#
#40
b100 &
b0 '
#44
0#
#49
0!
13
b101 /
0"
16
b100 0
1#
#50
b1 '
#54
0#
#59
1!
03
12
1"
b110 /
b101 0
14
1#
#60
0!
13
01
b11 /
0"
1%
b10 '
#64
0#
#69
02
1!
03
1"
b0 /
15
06
b11 0
1#
#70
0!
0"
0%
b11 '
#74
0#
#79
1!
11
1"
b100 /
b0 0
05
04
1#
#80
0!
13
01
b1 /
0"
1%
b101 &
b0 '
#84
0#
#89
03
12
b10 /
14
b1 0
1#
#90
13
1!
02
11
b101 /
1"
0%
b1 '
#94
0#
#99
03
12
b110 /
b101 0
16
1#
#100
0!
13
01
b11 /
0"
1%
b10 '
#104
0#
#109
02
1!
03
1"
b0 /
15
06
b11 0
1#
#110
0!
0"
0%
b11 '
#114
0#
#119
1!
11
1"
b100 /
b0 0
05
04
1#
#120
b110 &
b0 '
#124
0#
#129
0!
13
b101 /
0"
16
b100 0
1#
#130
1!
1"
1%
b1 '
#134
0#
#139
0!
12
01
b11 /
0"
b101 0
14
1#
#140
b10 '
#144
0#
#149
02
1!
03
1"
b0 /
15
06
b11 0
1#
#150
0!
0"
0%
b11 '
#154
0#
#159
1!
11
1"
b100 /
b0 0
05
04
1#
#160
0!
13
01
b1 /
0"
1%
b111 &
b0 '
#164
0#
#169
03
12
b10 /
14
b1 0
1#
#170
b1 '
#174
0#
#179
13
1!
b11 /
1"
b10 0
15
04
1#
#180
b10 '
#184
0#
#189
03
02
b0 /
14
b11 0
1#
#190
0!
0"
0%
b11 '
#194
0#
#199
1!
11
1"
b100 /
b0 0
05
04
1#
#200
b1000 &
b0 '
#204
0#
#209
0!
13
b101 /
0"
16
b100 0
1#
#210
b1 '
#214
0#
#219
1!
03
12
1"
b110 /
b101 0
14
1#
#220
b10 '
#224
0#
#229
0!
02
01
b0 /
04
15
b110 0
1#
#230
0"
1%
b11 '
#234
0#
#239
13
b1 /
b0 0
06
05
1#
#240
b1001 &
b0 '
#244
0#
#249
03
12
b10 /
14
b1 0
1#
#250
13
1!
02
11
b101 /
1"
0%
b1 '
#254
0#
#259
03
12
b110 /
b101 0
16
1#
#260
b10 '
#264
0#
#269
0!
02
01
b0 /
04
15
b110 0
1#
#270
0"
1%
b11 '
#274
0#
#279
13
b1 /
b0 0
06
05
1#
#280
1!
03
11
1"
b100 /
0%
b1010 &
b0 '
#284
0#
#289
0!
13
b101 /
0"
16
b100 0
1#
#290
1!
1"
1%
b1 '
#294
0#
#299
0!
12
01
b11 /
0"
b101 0
14
1#
#300
1!
03
11
1"
b110 /
0%
b10 '
#304
0#
#309
0!
02
01
b0 /
04
15
b110 0
1#
#310
0"
1%
b11 '
#314
0#
#319
13
b1 /
b0 0
06
05
1#
#320
b1011 &
b0 '
#324
0#
#329
03
12
b10 /
14
b1 0
1#
#330
b1 '
#334
0#
#339
13
1!
b11 /
1"
b10 0
15
04
1#
#340
0!
0"
0%
b10 '
#344
0#
#349
03
02
b0 /
14
b11 0
1#
#350
1!
1"
1%
b11 '
#354
0#
#359
13
0!
b1 /
0"
b0 0
05
04
1#
#360
1!
03
11
1"
b100 /
0%
b1100 &
b0 '
#364
0#
#369
0!
13
b101 /
0"
16
b100 0
1#
#370
b1 '
#374
0#
#379
1!
03
12
1"
b110 /
b101 0
14
1#
#380
0!
13
01
b11 /
0"
1%
b10 '
#384
0#
#389
02
1!
03
1"
b0 /
15
06
b11 0
1#
#390
b11 '
#394
0#
#399
13
0!
b1 /
0"
b0 0
05
04
1#
#400
b1101 &
b100 '
