數位電路設計/Lab3/code/Lab3_D_Latch_gatelevel.v
module Lab3_D_Latch_gatelevel (input D, E, output Q, Qb);
    wire D, E;
    wire Q, Qb;
    wire D_inv, and_result1, and_result2;
    not #(1) not1(D_inv, D);
    and #(1) and1(and_result1, D_inv, E);
    and #(1) and2(and_result2, E, D);
    nor #(1) nor1(Q, and_result1, Qb);
    nor #(1) nor2(Qb, and_result2, Q);
endmodule

數位電路設計/Lab3/code/t_Lab3_D_Latch_gatelevel.v
module t_Lab3_D_Latch_gatelevel();

reg D, E;
wire Q, Qb ;
Lab3_D_Latch_gatelevel D_latch(D, E, Q, Qb);

    initial fork
        #0 D = 0; 
        #0 E = 0;
        #5 E = 1;
        #10 E = 0;
        #15 D = 1;
        #20 E = 1;
        #25 D = 0; 
        #25 E = 0;
        #30 E = 1;
        #35 E = 0;
        #50 D = 1; 
        #50 E = 1;
        #51 E = 0;
        #55 E = 1;   
        #60 $finish;
    join
    initial begin
		$dumpfile("t_Lab3_D_Latch_gatelevel.vcd");
		$dumpvars;
	end



endmodule

數位電路設計/Lab3/code/t_Lab3_D_Latch_gatelevel.vcd
$date
	Sat May 27 01:17:35 2023
$end
$version
	Icarus Verilog
$end
$timescale
	1s
$end
$scope module t_Lab3_D_Latch_gatelevel $end
$var wire 1 ! Qb $end
$var wire 1 " Q $end
$var reg 1 # D $end
$var reg 1 $ E $end
$scope module D_latch $end
$var wire 1 # D $end
$var wire 1 % D_inv $end
$var wire 1 $ E $end
$var wire 1 " Q $end
$var wire 1 ! Qb $end
$var wire 1 & and_result1 $end
$var wire 1 ' and_result2 $end
$upscope $end
$upscope $end
$enddefinitions $end
$comment Show the parameter values. $end
$dumpall
$end
#0
$dumpvars
x'
x&
x%
0$
0#
x"
x!
$end
#1
1%
0&
0'
#5
1$
#6
1&
#7
0"
#8
1!
#10
0$
#11
0&
#15
1#
#16
0%
#20
1$
#21
1'
#22
0!
#23
1"
#25
0#
0$
#26
1%
0'
#30
1$
#31
1&
#32
0"
#33
1!
#35
0$
#36
0&
#50
1#
1$
#51
0%
1&
1'
0$
#52
0!
0&
0'
#53
1"
1!
#54
0!
0"
#55
1"
1!
1$
#56
0!
0"
1'
#57
1"
